README.md
setup.cfg
setup.py
distributions/Binomialdistribution.py
distributions/Gaussiandistribution.py
distributions/Generaldistribution.py
distributions/__init__.py
uuid_distributions.egg-info/PKG-INFO
uuid_distributions.egg-info/SOURCES.txt
uuid_distributions.egg-info/dependency_links.txt
uuid_distributions.egg-info/not-zip-safe
uuid_distributions.egg-info/top_level.txt