Metadata-Version: 1.0
Name: uuid-distributions
Version: 0.1
Summary: uuid-Gaussian distributions
Home-page: UNKNOWN
Author: UNKNOWN
Author-email: UNKNOWN
License: UNKNOWN
Platform: UNKNOWN
